<?xml version="1.0" encoding="UTF-8"?>


<Level name="Level 1" xmloverlaypath="src/vooga/games/mariogame/resources/overlays/GameOverlays.xml">

	<SpriteGroups>
		<SpriteGroup name="marioGroup">
			<RegularSprite name="vooga.games.mariogame.MarioSprite" random="false" x="10" y="100" vx="0" vy="0" quantity="1">
				<Visual name= "marioMovement"/>
			</RegularSprite>
		</SpriteGroup>
		
		<SpriteGroup name="goombaGroup">
			<SpawnedSprite name="vooga.games.mariogame.Enemy" random="true" xMin="50" xMax="1000" yMin="50" yMax="50" vxRange="1" vyRange="1" quantity="3">
				<Visual name="Goomba"/>
			</SpawnedSprite>
		</SpriteGroup>
	</SpriteGroups>
	
	<Map>
		<MapGroup name = "Map0">
			<Association char = "F" object = "vooga.games.mariogame.tiles.IndestructibleTile" image = "Grass Tile"></Association>
			<Association char = "D" object = "vooga.games.mariogame.tiles.IndestructibleTile" image = "Dirt Tile"></Association>
			<Association char = "B" object = "vooga.games.mariogame.tiles.BreakTile" image = "Break Tile"></Association>
			<Association char = "C" object = "vooga.games.mariogame.tiles.ChangingTile" image = "Item Tile 1"></Association>
			<Association char = "G" object = "vooga.games.mariogame.tiles.ItemTile" image = "Item Tile 2"></Association>
			<Association char = "S" object = "vooga.games.mariogame.tiles.CoinTile" image = "Item Tile 1"></Association>
		</MapGroup>	
	</Map>
	
	<Background>
		<Visual name="Space BG" />
	</Background>
	
	<Music>
		<Sound name="Level Music"/>
	</Music>
	
</Level>