<?xml version="1.0" encoding="UTF-8"?>
<Level name="jumper" xmloverlaypath="src/vooga/games/jumper/resources/overlays.xml">

	<SpriteGroups>

		<SpriteGroup name="doodleSprite">
			<Sprite class="vooga.games.jumper.sprites.DoodleSprite" random="false" x="400" y="0" vx="0" vy="0" quantity="1">
				<Visual name = "leftDoodle" />
			</Sprite>
		</SpriteGroup>
		
		
		<SpriteGroup name="normalBlocks">
			<Sprite class="vooga.games.jumper.sprites.NormalBlock" random="true" xMin="100" xMax="300" yMin="0" yMax="600" vxMin="0" vxMax="1" vyMin="-1" vyMax="1" quantity="50">
				<Visual name="platformGreen"/>
			</Sprite>
		</SpriteGroup>
		
		
		
	</SpriteGroups>
	
	<Events></Events>
	
	<Rules>
		<Rule name="Gravity" class="vooga.games.jumper.rules.Gravity">
			<SpriteGroup name="doodleSprite" />
		</Rule>
		
		<Rule name="Floor" class="vooga.games.jumper.rules.Floor">
			<SpriteGroup name="doodleSprite" />
		</Rule>
		<Rule name="RightWall" class="vooga.games.jumper.rules.RightWall">
			<SpriteGroup name="doodleSprite" />
		</Rule>
		<Rule name="LeftWall" class="vooga.games.jumper.rules.LeftWall">
			<SpriteGroup name="doodleSprite" />
		</Rule>
		<Rule name="WallBounce" class="vooga.games.jumper.rules.WallBounce">
			<SpriteGroup name="normalBlocks" />
		</Rule>
		
	</Rules>

	<CollisionGroups>
		
	</CollisionGroups>
	
	<Backgrounds>
		<Background name = "backgroundImage" />
	</Backgrounds>
	
	<Music />
	<Map />

</Level>